lsyflaskmicroapp_sms/__init__.py
lsyflaskmicroapp_sms/orm.py
lsyflaskmicroapp_sms/apis/__init__.py
lsyflaskmicroapp_sms/apis/sms_group.py
lsyflaskmicroapp_sms/apis/sms_message.py
lsyflaskmicroapp_sms/apis/sms_person.py
lsyflaskmicroapp_sms/apis/sms_receive.py
lsyflaskmicroapp_sms/apis/sms_send.py
lsyflaskmicroapp_sms/entitys/__init__.py
lsyflaskmicroapp_sms/entitys/sms_group.py
lsyflaskmicroapp_sms/entitys/sms_message.py
lsyflaskmicroapp_sms/entitys/sms_person.py
lsyflaskmicroapp_sms/entitys/sms_receive.py
lsyflaskmicroapp_sms/entitys/sms_send.py
lsyflaskmicroapp_sms/models/__init__.py
lsyflaskmicroapp_sms/models/sms_group.py
lsyflaskmicroapp_sms/models/sms_message.py
lsyflaskmicroapp_sms/models/sms_person.py
lsyflaskmicroapp_sms/models/sms_receive.py
lsyflaskmicroapp_sms/models/sms_send.py
lsyflaskmicroapp_sms/schemas/__init__.py
lsyflaskmicroapp_sms/schemas/sms_group.py
lsyflaskmicroapp_sms/schemas/sms_message.py
lsyflaskmicroapp_sms/schemas/sms_person.py
lsyflaskmicroapp_sms/schemas/sms_receive.py
lsyflaskmicroapp_sms/schemas/sms_send.py
lsyflaskmicroapp_sms-1.0.0.dist-info/METADATA
lsyflaskmicroapp_sms-1.0.0.dist-info/WHEEL
lsyflaskmicroapp_sms-1.0.0.dist-info/top_level.txt
lsyflaskmicroapp_sms-1.0.0.dist-info/RECORD
